LICENSE
MANIFEST.in
README.rst
setup.cfg
setup.py
versioneer.py
tpDcc/__init__.py
tpDcc/tools/__init__.py
tpDcc/tools/datalibrary/__init__.py
tpDcc/tools/datalibrary/__logging__.ini
tpDcc/tools/datalibrary/__version__.py
tpDcc/tools/datalibrary/_version.py
tpDcc/tools/datalibrary/core/__init__.py
tpDcc/tools/datalibrary/core/client.py
tpDcc/tools/datalibrary/core/consts.py
tpDcc/tools/datalibrary/core/factory.py
tpDcc/tools/datalibrary/core/settings.py
tpDcc/tools/datalibrary/core/tool.py
tpDcc/tools/datalibrary/core/toolset.py
tpDcc/tools/datalibrary/core/utils.py
tpDcc/tools/datalibrary/core/views/__init__.py
tpDcc/tools/datalibrary/core/views/dataitem.py
tpDcc/tools/datalibrary/core/views/item.py
tpDcc/tools/datalibrary/data/__init__.py
tpDcc/tools/datalibrary/data/base.py
tpDcc/tools/datalibrary/data/folder.py
tpDcc/tools/datalibrary/data/group.py
tpDcc/tools/datalibrary/data/image.py
tpDcc/tools/datalibrary/dccs/__init__.py
tpDcc/tools/datalibrary/dccs/max/__init__.py
tpDcc/tools/datalibrary/dccs/max/server.py
tpDcc/tools/datalibrary/dccs/maya/__init__.py
tpDcc/tools/datalibrary/dccs/maya/server.py
tpDcc/tools/datalibrary/dccs/maya/core/__init__.py
tpDcc/tools/datalibrary/dccs/maya/core/factory.py
tpDcc/tools/datalibrary/dccs/maya/data/__init__.py
tpDcc/tools/datalibrary/dccs/maya/data/dataitem.py
tpDcc/tools/datalibrary/dccs/maya/menus/__init__.py
tpDcc/tools/datalibrary/dccs/maya/menus/sets.py
tpDcc/tools/datalibrary/dccs/maya/widgets/__init__.py
tpDcc/tools/datalibrary/dccs/maya/widgets/load.py
tpDcc/tools/datalibrary/dccs/maya/widgets/save.py
tpDcc/tools/datalibrary/widgets/__init__.py
tpDcc/tools/datalibrary/widgets/export.py
tpDcc/tools/datalibrary/widgets/listview.py
tpDcc/tools/datalibrary/widgets/load.py
tpDcc/tools/datalibrary/widgets/mixinview.py
tpDcc/tools/datalibrary/widgets/preview.py
tpDcc/tools/datalibrary/widgets/save.py
tpDcc/tools/datalibrary/widgets/search.py
tpDcc/tools/datalibrary/widgets/sequence.py
tpDcc_tools_datalibrary.egg-info/PKG-INFO
tpDcc_tools_datalibrary.egg-info/SOURCES.txt
tpDcc_tools_datalibrary.egg-info/dependency_links.txt
tpDcc_tools_datalibrary.egg-info/not-zip-safe
tpDcc_tools_datalibrary.egg-info/requires.txt
tpDcc_tools_datalibrary.egg-info/top_level.txt