Metadata-Version: 2.1
Name: tpDcc-tools-datalibrary
Version: 0.0.1
Summary: Tool to manage DCC related data in an easy way.
Home-page: https://github.com/tpDcc/tpDcc-tools-datalibrary
Author: Tomas Poveda
Author-email: tpovedatd@gmail.com
License: MIT
Platform: UNKNOWN
Provides-Extra: dev
Provides-Extra: test
